Metadata-Version: 2.1
Name: test-opsramp-analytics-utils
Version: 2.4.6
Summary: OpsRamp Analytics SDK
Home-page: https://github.com/opsramp/analytics-sdk
Author: OpsRamp
Author-email: opsramp@support.com
License: UNKNOWN
Platform: UNKNOWN
Classifier: Programming Language :: Python :: 3
Classifier: License :: OSI Approved :: MIT License
Classifier: Operating System :: OS Independent
Requires-Python: >=3.6
Requires-Dist: Werkzeug (==2.0.3)
Requires-Dist: boto3 (==1.17.51)
Requires-Dist: botocore (==1.20.51)
Requires-Dist: dash (==1.16.2)
Requires-Dist: openpyxl (==3.0.7)
Requires-Dist: pyjwt (==2.0.1)
Requires-Dist: requests (==2.24.0)
